hinbdev/__init__.py
hinbdev/_nbdev.py
hinbdev/core.py
hinbdev-0.0.1.dist-info/LICENSE
hinbdev-0.0.1.dist-info/METADATA
hinbdev-0.0.1.dist-info/WHEEL
hinbdev-0.0.1.dist-info/entry_points.txt
hinbdev-0.0.1.dist-info/top_level.txt
hinbdev-0.0.1.dist-info/RECORD
