Metadata-Version: 2.1
Name: hinbdev
Version: 0.0.1
Summary: A description of your project
Home-page: https://github.com/sky1ove/hinbdev/tree/main/
Author: sky1ove
Author-email: lcai888666@gmail.com
License: Apache Software License 2.0
Keywords: some keywords
Platform: UNKNOWN
Classifier: Development Status :: 3 - Alpha
Classifier: Intended Audience :: Developers
Classifier: Natural Language :: English
Classifier: Programming Language :: Python :: 3.6
Classifier: Programming Language :: Python :: 3.7
Classifier: Programming Language :: Python :: 3.8
Classifier: License :: OSI Approved :: Apache Software License
Requires-Python: >=3.6
Requires-Dist: pip
Requires-Dist: packaging
Provides-Extra: dev
